{"id":"5c2b9afa5513850017f82dc0","title":"しばらく書いてなかった - diary.jgs.me","image":null,"created":1379872380,"updated":1563737297,"lines":[{"id":"5c2b9afa4ade4d000077e176","text":"しばらく書いてなかった - diary.jgs.me","created":1379872380,"updated":1563737273},{"id":"5c2b9afa4ade4d000077e177","text":"むちゃくちゃ忙しくて、自室に戻ってきてバタンキューという感じだったので書いてなかった。","created":1379872380,"updated":1379872380},{"id":"5c2b9afa4ade4d000077e178","text":"[すきやき]のあと、[カナザワ]に行ったり学校行ったり仕事行ったり同期のプロダクトやったり鬼忙だった。","created":1379872380,"updated":1563737283},{"id":"5c2b9afa4ade4d000077e179","text":"それから[デブサミ関西]にも行ってきた。ちょっと自分のいる世界と違う世界でいろいろ新鮮だった反面、いろいろ思うところもあった。","created":1379872380,"updated":1563737289},{"id":"5c2b9afa4ade4d000077e17a","text":"今月一杯はしばらく忙しそう。","created":1379872380,"updated":1379872380},{"id":"5d34bcc94ade4d00004ff155","text":"","created":1563737291,"updated":1563737291},{"id":"5c2b9afa4ade4d000077e17b","text":"September 23rd, 2013 2:53am","created":1379872380,"updated":1379872380},{"id":"5c2b9afa4ade4d000077e17c","text":"[* original: http://diary.jgs.me/post/61977403435]","created":1379872380,"updated":1379872380},{"id":"5c2b9afa4ade4d000077e17d","text":"#20130923 #0923","created":1379872380,"updated":1563737297},{"id":"5d34bccd4ade4d00004ff156","text":"","created":1563737294,"updated":1563737294}]}