{"id":"5c2b9af65513850017f82cd2","title":"rubyのインストール中なので - diary.jgs.me","image":null,"created":1414566300,"updated":1576324057,"lines":[{"id":"5c2b9af64ade4d000077d4d5","text":"rubyのインストール中なので - diary.jgs.me","created":1414566300,"updated":1547546549},{"id":"5c2b9af64ade4d000077d4d6","text":"仕事で[レールズ]することが決まって、社用PCに[ルビー]を入れている。いれている間ヒマなので、ふと思い出したことを書く。","created":1414566300,"updated":1547546561},{"id":"5c2b9af64ade4d000077d4d7","text":"少し前ぐらいに、どこだったか忘れたどこかで、[高校生]か[大学生]ぐらいの若い女の子が「あたし[リベンジポルノ]を一番恐れてるので[ハメ撮り]とか絶対にさせません」みたいなことをまあまあ大きな声で話してて、僕は内心(いい心掛けです、その[インターネットリテラシ]がインターネットを救うのです)などと聞き耳を立てていたら話し相手の男が「へー、そんなのがあるんだー、まあイヤだよね〜」みたいな[テンション]で応えていて(おいてめえ！てめえみたいな無頓着な不届き者がいるから問題になんだろボケ！)というような心持ちで聞いていた。","created":1414566300,"updated":1547546597},{"id":"5c2b9af64ade4d000077d4d8","text":"[性暴力]の問題に対しては、[tumblr民]としては[dsbd]にいくらか紛れているんじゃないか感が否めなくてあまり大きな声で言えない、という感覚でいる。同様に[バイラル]関係でもろもろ[メディア]が叩かれているのにもtumblr民としてはあまり穏やかな心境ではいられないのが難しいところである。","created":1414566300,"updated":1547546620},{"id":"5c2b9af64ade4d000077d4d9","text":"まあその、[インターネット]、各々が[リテラシ]を持って生きていってほしいなと、そういうゆるい話にしか落ちないのです。","created":1414566300,"updated":1547546631},{"id":"5c2b9af64ade4d000077d4da","text":"October 29th, 2014 4:05pm","created":1414566300,"updated":1414566300},{"id":"5c2b9af64ade4d000077d4db","text":"[* original: http://diary.jgs.me/post/101241293314]","created":1414566300,"updated":1414566300},{"id":"5c2b9af64ade4d000077d4dc","text":"#20141029 #1029","created":1414566300,"updated":1571829248},{"id":"5c3db0094ade4d0000524e8b","text":"","created":1547546633,"updated":1547546633}]}