{"id":"5c6a3349595ea90017209d6d","title":"UCDとDDD - ユースケースからユーザー中心について考える // Speaker Deck - github.com/e-jigsaw/web","image":null,"created":1463376788,"updated":1569048033,"lines":[{"id":"5c6a33494ade4d00009b34df","text":"UCDとDDD - ユースケースからユーザー中心について考える // Speaker Deck - github.com/e-jigsaw/web","created":1463376788,"updated":1463376788},{"id":"5c6a33494ade4d00009b34e0","text":"[UCDとDDD - ユースケースからユーザー中心について考える // Speaker Deck https://speakerdeck.com/tyshgc/ucdtoddd-yusukesukarayuzazhong-xin-nituitekao-eru]","created":1463376788,"updated":1463376788},{"id":"5c6a33494ade4d00009b34e2","text":"","created":1463376788,"updated":1463376788},{"id":"5c6a33494ade4d00009b34e3","text":"[ddd] [design]","created":1463376788,"updated":1463376788},{"id":"5c6a33494ade4d00009b34e5","text":"#20160516 #0516","created":1463376788,"updated":1463376788}]}