{"id":"5d5c125d535aa6001761fd67","title":"GIFはポップカルチャーの思い出のための媒体から、研究やジャーナリズムといった真剣な用途のツールへと発展し、その語彙的同一性も変化している","image":null,"created":1566315104,"updated":1566315234,"lines":[{"id":"5d5c125d535aa6001761fd67","text":"GIFはポップカルチャーの思い出のための媒体から、研究やジャーナリズムといった真剣な用途のツールへと発展し、その語彙的同一性も変化している","created":1566315104,"updated":1566315104},{"id":"5d5c12624ade4d0000f9f4cd","text":"[Gyazo on Rails Developer Talk に行ってきた - dev.jgs.me]","created":1566315106,"updated":1566315131},{"id":"5d5c12724ade4d0000f9f4d0","text":"","created":1566315123,"updated":1566315123},{"id":"5d5c12e04ade4d0000d58ff0","text":"#GIF","created":1566315233,"updated":1566315234},{"id":"5d5c12624ade4d0000f9f4ce","text":"#20190821 #0821","created":1566315106,"updated":1566315121},{"id":"5d5c12624ade4d0000f9f4cf","text":"","created":1566315106,"updated":1566315106}]}