{"id":"5d73dc4becc0400017dd5f9b","title":"CI","image":null,"created":1567874127,"updated":1567874171,"lines":[{"id":"5d73dc4becc0400017dd5f9b","text":"CI","created":1567874127,"updated":1567874127},{"id":"5d73dc4e4ade4d00005c4001","text":"[Continuous Integration] の時と [Chaos Innoculation] の時がある","created":1567874127,"updated":1567874166},{"id":"5d73dc4f4ade4d00005c4002","text":"","created":1567874127,"updated":1567874127},{"id":"5d73dc774ade4d00005c4003","text":"#曖昧さ回避","created":1567874167,"updated":1567874171},{"id":"5d73dc774ade4d00005c4004","text":"","created":1567874167,"updated":1567874167}]}