{"id":"5d91a2e86cdbee00177635bc","title":"アニメとかゲームとか何かを好きというと、謎に「マニア」とか「芸能界屈指の！」とか、「めちゃくちゃ上手い・詳しい！」みたいな感じで台本書かれること多いのですが、ぼくはただ好きなだけです。","image":null,"created":1569825512,"updated":1569825544,"lines":[{"id":"5d91a2e86cdbee00177635bc","text":"アニメとかゲームとか何かを好きというと、謎に「マニア」とか「芸能界屈指の！」とか、「めちゃくちゃ上手い・詳しい！」みたいな感じで台本書かれること多いのですが、ぼくはただ好きなだけです。","created":1569825512,"updated":1569825526},{"id":"5d91a2e84ade4d00001595b9","text":"[最上もがさんはTwitterを使っています: 「アニメとかゲームとか何かを好きというと、謎に「マニア」とか「芸能界屈指の！」とか、「めちゃくちゃ上手い・詳しい！」みたいな感じで台本書かれること多いのですが、ぼくはただ好きなだけです。そこまで極めてるわけじゃないです全て…そもそも時間がない。。」 / Twitter https://twitter.com/mogatanpe/status/1177095221433159680?s=09]","created":1569825512,"updated":1569825512},{"id":"5d91a2e84ade4d00001595ba","text":"> [アニメ]とか[ゲーム]とか何かを好きというと、謎に「[マニア]」とか「芸能界屈指の！」とか、「めちゃくちゃ上手い・詳しい！」みたいな感じで台本書かれること多いのですが、ぼくはただ好きなだけです。","created":1569825512,"updated":1569825539},{"id":"5d91a2e84ade4d00001595bb","text":"","created":1569825512,"updated":1569825512},{"id":"5d91a2e84ade4d00001595bc","text":"[最上もが]","created":1569825512,"updated":1569825544},{"id":"5d91a2e84ade4d00001595bd","text":"#20190930 #0930","created":1569825512,"updated":1569825512},{"id":"5d91a2e84ade4d00001595be","text":"","created":1569825512,"updated":1569825512}]}