{"id":"5dafce89ad897e0017aa282d","title":"React NativeをWebに持ってくることの意味 - ナカザンドットネット","image":"https://gyazo.com/9a116af4f1bfe01e04aa31f036571ff9/raw","created":1571802763,"updated":1571802773,"lines":[{"id":"5dafce89ad897e0017aa282d","text":"React NativeをWebに持ってくることの意味 - ナカザンドットネット","created":1571802763,"updated":1571802763},{"id":"5dafce8a4ade4d000070c18b","text":"[React NativeをWebに持ってくることの意味 - ナカザンドットネット http://blog.nkzn.info/entry/2018/05/29/210030]","created":1571802763,"updated":1571802763},{"id":"5dafce8a4ade4d000070c18c","text":"[https://gyazo.com/9a116af4f1bfe01e04aa31f036571ff9 http://blog.nkzn.info/entry/2018/05/29/210030]","created":1571802763,"updated":1571802763},{"id":"5dafce8a4ade4d000070c18d","text":"","created":1571802763,"updated":1571802763},{"id":"5dafce8a4ade4d000070c18e","text":"\t[React Native for Web] の意義とは？","created":1571802763,"updated":1571802763},{"id":"5dafce8a4ade4d000070c18f","text":" \tReact Native は #GUI の[抽象]になってる","created":1571802763,"updated":1571802763},{"id":"5dafce8a4ade4d000070c190","text":"  [iOS]/[Android] に書き出すように [Web] にも書き出そうという話","created":1571802763,"updated":1571802763},{"id":"5dafce8a4ade4d000070c191","text":"","created":1571802763,"updated":1571802763},{"id":"5dafce8a4ade4d000070c192","text":"[React Native] #React #JavaScript","created":1571802763,"updated":1571802763},{"id":"5dafce8a4ade4d000070c194","text":"#20180531 #0531","created":1571802763,"updated":1571802769},{"id":"5dafce8a4ade4d000070c195","text":"","created":1571802763,"updated":1571802763}]}