{"id":"5dafd0523e1c1700178e3e58","title":"GoogleChromeLabs/comlink: Comlink makes WebWorkers enjoyable.","image":"https://gyazo.com/f4ca4f6fe44bd8831a4636c64d0c3821/raw","created":1571803219,"updated":1571803225,"lines":[{"id":"5dafd0523e1c1700178e3e58","text":"GoogleChromeLabs/comlink: Comlink makes WebWorkers enjoyable.","created":1571803219,"updated":1571803219},{"id":"5dafd0524ade4d000070c1b3","text":"[GoogleChromeLabs/comlink: Comlink makes WebWorkers enjoyable. https://github.com/GoogleChromeLabs/comlink]","created":1571803219,"updated":1571803219},{"id":"5dafd0524ade4d000070c1b4","text":"[https://gyazo.com/f4ca4f6fe44bd8831a4636c64d0c3821 https://github.com/GoogleChromeLabs/comlink]","created":1571803219,"updated":1571803219},{"id":"5dafd0524ade4d000070c1b6","text":"#WebWorker のラッパー [Google Chrome] 製","created":1571803219,"updated":1571803219},{"id":"5dafd0524ade4d000070c1b7","text":"","created":1571803219,"updated":1571803219},{"id":"5dafd0524ade4d000070c1b8","text":"#20181026 #1026","created":1571803219,"updated":1571803225},{"id":"5dafd0524ade4d000070c1b9","text":"","created":1571803219,"updated":1571803219}]}