{"id":"5dbbc5b4baac2300171cc59d","title":"JavaScript at Tumblr — Flow and TypeScript","image":"https://gyazo.com/f5d8b4758406f3121f8fc4c7d79750db/raw","created":1572586938,"updated":1572586939,"lines":[{"id":"5dbbc5b4baac2300171cc59d","text":"JavaScript at Tumblr — Flow and TypeScript","created":1572586938,"updated":1572586939},{"id":"5dbbc5b54ade4d00009f428d","text":"[JavaScript at Tumblr — Flow and TypeScript https://javascript.tumblr.com/post/165082071937/flow-and-typescript]","created":1572586939,"updated":1572586939},{"id":"5dbbc5b54ade4d00009f428e","text":"[https://gyazo.com/f5d8b4758406f3121f8fc4c7d79750db https://javascript.tumblr.com/post/165082071937/flow-and-typescript]","created":1572586939,"updated":1572586939},{"id":"5dbbc5b54ade4d00009f428f","text":"","created":1572586939,"updated":1572586939},{"id":"5dbbc5b54ade4d00009f4290","text":"#Tumblr #JavaScript #FlowType #TypeScript","created":1572586939,"updated":1572586939},{"id":"5dbbc5b54ade4d00009f4291","text":"#20170915 #0915","created":1572586939,"updated":1572586939},{"id":"5dbbc5b54ade4d00009f4292","text":"","created":1572586939,"updated":1572586939}]}