{"id":"5e0196a154e77a0017a919db","title":"私立恵比寿中学、安本彩花も共に歌ったバンドセットの「大学芸会」（ライブレポート / 写真70枚） - 音楽ナタリー","image":"https://gyazo.com/73f3b2c4ae6ee98d24754e84fad67eef/raw","created":1577162402,"updated":1577162601,"lines":[{"id":"5e0196a154e77a0017a919db","text":"私立恵比寿中学、安本彩花も共に歌ったバンドセットの「大学芸会」（ライブレポート / 写真70枚） - 音楽ナタリー","created":1577162402,"updated":1577162402},{"id":"5e0196a14ade4d0000221b59","text":"[私立恵比寿中学、安本彩花も共に歌ったバンドセットの「大学芸会」（ライブレポート / 写真70枚） - 音楽ナタリー https://natalie.mu/music/news/360732]","created":1577162402,"updated":1577162402},{"id":"5e0196a14ade4d0000221b5a","text":"[https://gyazo.com/73f3b2c4ae6ee98d24754e84fad67eef]","created":1577162402,"updated":1577162471},{"id":"5e0196e74ade4d0000221b5f","text":"> ライブ中盤の幕間にはステージ後方のスクリーンに、エビ中メンバーがレッスンに励む様子を捉えたVTRが流された。そして場面が昼下がりの公園に切り替わると、そこには活動休止中のメンバー・[安本彩花]の姿が。映像は安本が1人物思いにふけるシーンで一旦終了。","created":1577162471,"updated":1577162550},{"id":"5e0196a14ade4d0000221b5b","text":"","created":1577162402,"updated":1577162402},{"id":"5e0197094ade4d0000221b60","text":"> VTRの後編では安本がスタジオへと向かう様子が映し出され、暗転ののちに始まった初のメンバー作詞曲「[HISTORY]」では6分割されたスクリーンに安本を含む6人のアップが浮かぶ。リアルタイムで歌う5人と、スタジオで歌う安本。エビ中の歴史を紡いだ「HISTORY」を歌う6人の声と表情に、場内は感動的なムードに包まれた。","created":1577162505,"updated":1577162555},{"id":"5e01972b4ade4d0000221b62","text":"","created":1577162539,"updated":1577162539},{"id":"5e01972b4ade4d0000221b63","text":"> 熱烈なアンコールに応えて再びステージに登場したエビ中は、[ももいろクローバーZ]とのコラボ曲「[COLOR]」でライブを再開。勢いそのままにインディーズ時代の楽曲「[永遠に中学生]」を元気いっぱいに届けた。場内をハッピーな空気で満たしたエビ中は、最後に「[なないろ]」をパフォーマンス。","created":1577162539,"updated":1577162581},{"id":"5e0197094ade4d0000221b61","text":"","created":1577162505,"updated":1577162505},{"id":"5e0197564ade4d0000221b64","text":"行ってないけどこんな演出泣いてまうな.....","created":1577162583,"updated":1577162601},{"id":"5e0197564ade4d0000221b65","text":"","created":1577162583,"updated":1577162583},{"id":"5e0196a14ade4d0000221b5c","text":"[私立恵比寿中学]","created":1577162402,"updated":1577162479},{"id":"5e0196a14ade4d0000221b5d","text":"#20191224 #1224","created":1577162402,"updated":1577162402},{"id":"5e0196a14ade4d0000221b5e","text":"","created":1577162402,"updated":1577162402}]}