{"id":"5e5fabdc829fc100172e34c7","title":"PoolTogether チケット買ってみた","image":"https://gyazo.com/d61bd48b6dd05e12b6ec217ac05c5e8e/raw","created":1583328224,"updated":1583331814,"lines":[{"id":"5e5fabdc829fc100172e34c7","text":"PoolTogether チケット買ってみた","created":1583328224,"updated":1583328240},{"id":"5e5fabe54ade4d0000a7af22","text":"from [20200211] #0211","created":1583328227,"updated":1583331814},{"id":"5e5fabe64ade4d0000a7af23","text":"[PoolTogether]","created":1583328228,"updated":1583328228},{"id":"5e5fabe64ade4d0000a7af24","text":"\t[https://gyazo.com/d61bd48b6dd05e12b6ec217ac05c5e8e]","created":1583328228,"updated":1583328228},{"id":"5e5fabe64ade4d0000a7af25","text":"\t試しにチケット買ってみた","created":1583328228,"updated":1583328228},{"id":"5e5fabe64ade4d0000a7af26","text":"\t\t当たる確率は `1 in 21,353` らしいのでむしろこんなところで運使いたくないのでむしろ当たらないでくれ〜みたいな気持ちになってきた","created":1583328228,"updated":1583328228}]}