{"id":"5f03a961d8925000249b272b","title":"苔（コケ）のインテリア コケリウム（苔テラリウム）専門通販サイト - KOKERIUM コケリウム","image":"https://gyazo.com/971470fa5424e899be3d4722a340bf9d/raw","created":1594075490,"updated":1594075531,"lines":[{"id":"5f03a961d8925000249b272b","text":"苔（コケ）のインテリア コケリウム（苔テラリウム）専門通販サイト - KOKERIUM コケリウム","created":1594075490,"updated":1594075490},{"id":"5f03a9614ade4d0000251c38","text":"[苔（コケ）のインテリア コケリウム（苔テラリウム）専門通販サイト - KOKERIUM コケリウム https://www.kokerium.com/]","created":1594075490,"updated":1594075490},{"id":"5f03a9614ade4d0000251c39","text":"[https://gyazo.com/971470fa5424e899be3d4722a340bf9d]","created":1594075490,"updated":1594075509},{"id":"5f03a9754ade4d00008b859d","text":"[観葉植物]ほしいな〜とおもってたけど、苔でもいいかもしれん","created":1594075509,"updated":1594075531},{"id":"5f03a9614ade4d0000251c3a","text":"","created":1594075490,"updated":1594075490},{"id":"5f03a9614ade4d0000251c3b","text":"[苔] [インテリア]","created":1594075490,"updated":1594075518},{"id":"5f03a9614ade4d0000251c3c","text":"#20200707 #0707","created":1594075490,"updated":1594075490},{"id":"5f03a9614ade4d0000251c3d","text":"","created":1594075490,"updated":1594075490}]}