{"id":"5f66cf48c0d17400216db581","title":"ザ・ボーイズ シーズン2楽しみにしてたんだけどさ","image":null,"created":1600573257,"updated":1600573262,"lines":[{"id":"5f66cf48c0d17400216db581","text":"ザ・ボーイズ シーズン2楽しみにしてたんだけどさ","created":1600573257,"updated":1600573257},{"id":"5f66cf484ade4d000009cff0","text":"from [20200904] #0904","created":1600573257,"updated":1600573262},{"id":"5f66cf484ade4d000009cff1","text":"[ザ・ボーイズ シーズン2]楽しみにしてたんだけどさ","created":1600573257,"updated":1600573257},{"id":"5f66cf484ade4d000009cff2","text":"\tまたネイティブじゃない日本語を話す役者が日本人の役で起用されてて複雑な気分","created":1600573257,"updated":1600573257},{"id":"5f66cf484ade4d000009cff3","text":"\t\t演じてくれてる人もがんばって日本語のセリフおぼえてくれてるんだし、あんまりくさしたくないんだけど","created":1600573257,"updated":1600573257},{"id":"5f66cf484ade4d000009cff4","text":"\t\t\t日本語なんだからわかるだろうってことなのか、字幕も日本語のところは字幕がないので聞き取りがムズくて困るし、やっぱあまりにもイントネーションが厳しすぎると作り物感が出てしまって萎える","created":1600573257,"updated":1600573257},{"id":"5f66cf484ade4d000009cff5","text":"\t\t[デアデビル]の件もあったし、やっぱなんか日本人とか日本語って軽視されてるんだなっておもってしまう","created":1600573257,"updated":1600573257},{"id":"5f66cf484ade4d000009cff6","text":"\t\t\t性的マイノリティと役者みたいな話もあるし、[BLM] みたいに声を上げていくしかないんかなあ","created":1600573257,"updated":1600573257},{"id":"5f66cf484ade4d000009cff7","text":"\t\t\t\tとはいえ[ザ・ボーイズ]という作品自体はめっちゃ面白いのであんま下げたくないし、うーん...","created":1600573257,"updated":1600573257},{"id":"5f66cf484ade4d000009cff8","text":"\t\t他の言語でもこういうことってあるんだろうか？","created":1600573257,"updated":1600573257},{"id":"5f66cf484ade4d000009cff9","text":"\t\tあと、[Twitter] で英語の発音について言及するとめっちゃ叩かれるみたいなんだけど、そことは分けて考えていいんだろうか","created":1600573257,"updated":1600573257}]}