{"id":"5f8165b661dd2e0023fedc58","title":"ザ・ボーイズ シーズン2完走","image":null,"created":1602315702,"updated":1634455105,"lines":[{"id":"5f8165b661dd2e0023fedc58","text":"ザ・ボーイズ シーズン2完走","created":1602315702,"updated":1602315702},{"id":"5f8165b64ade4d000072cdfe","text":"from [20201009] #1009","created":1602315702,"updated":1602315707},{"id":"5f8165b64ade4d000072cdff","text":"[ザ・ボーイズ シーズン2]完走","created":1602315702,"updated":1602315702},{"id":"5f8165b64ade4d000072ce00","text":"\t前話が公開された後一旦取り消されていたのを知って、早めにみておくことにした","created":1602315702,"updated":1602315702},{"id":"5f8165b64ade4d000072ce01","text":"\tシーズン3きたときにサッと思い出せるように書いておくと","created":1602315702,"updated":1602315702},{"id":"5f8165b64ade4d000072ce02","text":"\t\tボーイズの面々は放免になり、各々の暮らしへ戻った","created":1602315702,"updated":1602315702},{"id":"5f8165b64ade4d000072ce03","text":"\t\t\t[ヒューイ]はニューマン議員(コングレスって議員って意味だよね？)のスタッフに","created":1602315702,"updated":1634455002},{"id":"5f8165b64ade4d000072ce04","text":"\t\t\t[MM]は実家へ","created":1602315702,"updated":1634455008},{"id":"5f8165b64ade4d000072ce05","text":"\t\t\t[フレンチー]は[キミコ]と","created":1602315702,"updated":1634455013},{"id":"5f8165b64ade4d000072ce06","text":"\t\t\t[ブッチャー]は[CIA]の誘いを断って(だよね？)どこかへ","created":1602315702,"updated":1634455020},{"id":"5f8165b64ade4d000072ce07","text":"\t\t[セブン]の面々は散々","created":1602315702,"updated":1634455024},{"id":"5f8165b64ade4d000072ce08","text":"\t\t\t[ホームランダー]は息子を失い、飛行機の映像をネタに握られており、夜な夜なマスかいてる模様","created":1602315702,"updated":1634455029},{"id":"5f8165b64ade4d000072ce09","text":"\t\t\t[メイヴ]と[スターライト]はセブンに残留","created":1602315702,"updated":1634455036},{"id":"5f8165b64ade4d000072ce0a","text":"\t\t\t[ノワール]はまだ昏睡状態なのかな？","created":1602315702,"updated":1634455040},{"id":"5f8165b64ade4d000072ce0b","text":"\t\t\t[Aトレイン]が教会の差し金で復帰する模様","created":1602315702,"updated":1634455043},{"id":"5f8165b64ade4d000072ce0c","text":"\t\t\t[ディープ]は教会に中指を立てて去った","created":1602315702,"updated":1634455046},{"id":"5f8165b64ade4d000072ce0d","text":"\t\t\t[ストームフロント]は死んだ？かな？","created":1602315702,"updated":1634455050},{"id":"5f8165b64ade4d000072ce0e","text":"\t\tところで1話からずーっと潜んでいた遠隔爆破型の能力者は一体...?というのが実は恐らく次シリーズの伏線になってるという","created":1602315702,"updated":1602315702},{"id":"5f8165b64ade4d000072ce0f","text":"\t\t\t[ヴォート]を追い詰めていたニューマン議員がやっていたみたいで、爆破する時に目の色が変わるっぽいんだけど、議会の惨劇シーンでは素直にビビってただけのような...","created":1602315702,"updated":1634455061},{"id":"5f8165b64ade4d000072ce10","text":"\t\t\t\tそもそも議会の爆破にせよ、1話のマロリーの娘爆破にせよ、どういうモチベーションでやっていたのか...","created":1602315702,"updated":1602315702},{"id":"5f8165b64ade4d000072ce11","text":"\t\t\t\t\tまあ、[スーパーウォッチ]みたいなのを組織するのが目的みたいだったけど","created":1602315702,"updated":1634455069},{"id":"5f8165b64ade4d000072ce12","text":"\t\t\t\tしかもそこにひょっこり浸入してしまうヒューイの悪運よ....","created":1602315702,"updated":1602315702},{"id":"5f8165b64ade4d000072ce13","text":"\t最終回の感想","created":1602315702,"updated":1602315702},{"id":"5f8165b64ade4d000072ce14","text":"\t\tついに[ナチ残党]だと暴かれたストームフロント aka [リバティ]をタコ殴りにするキミコとメイヴとスターライトのシーンは爆笑してしまった","created":1602315702,"updated":1634455085},{"id":"5f8165b64ade4d000072ce15","text":"\t\t\tボーイズってタイトルだけど能力者なのはガールズっていう皮肉","created":1602315702,"updated":1602315702},{"id":"5f8165b64ade4d000072ce16","text":"\t\tホームランダーに同情の余地はないけど、かわいそうっちゃあかわいそう、あと大事な人を喪ったという意味ではブッチャーと鏡写しになってて、次シリーズでも効いてきそうな...","created":1602315702,"updated":1602315702},{"id":"5f8165b64ade4d000072ce17","text":"\t\tエドガーの考え方はまさに[新自由資本主義]的、もしくは[原始資本主義的]なのか","created":1602315702,"updated":1634455105},{"id":"5f8165b64ade4d000072ce18","text":"\t\t\tベッカとライアンを匿ってたのはホームランダーに対抗するためだったのだなぁ","created":1602315702,"updated":1602315702},{"id":"5f8165b64ade4d000072ce19","text":"\t\t\t\tとするならなんかヴォートに洗脳施設みたいなのを作って洗脳した方がよかったんでは、という気もするが","created":1602315702,"updated":1602315702},{"id":"5f8165b64ade4d000072ce1a","text":"\t\tブッチャーも人の子だったなあ","created":1602315702,"updated":1602315702},{"id":"5f8165b64ade4d000072ce1b","text":"\t\tストームフロントを[ナチズム]と結んだのはちょっと安直だった気もする","created":1602315702,"updated":1602315702},{"id":"5f8165b64ade4d000072ce1c","text":"\t\t\t[ドラマ版ウォッチメン]では直球に[KKK]を意識したつくりになってたのに対して、ナチだとちょっと弱いというか、今やかの国はナチズムや[ネオナチ]よりは KKK 的な[白人至上主義]の方が根深そうにおもう","created":1602315702,"updated":1602315702},{"id":"5f8165b64ade4d000072ce1d","text":"\t\tヒューイとアニーに証言を請われたメイヴの態度は結構自分と近いものを感じて、なんか改めようという気持ちになった","created":1602315702,"updated":1602315702},{"id":"5f8165b64ade4d000072ce1e","text":"\t\t\tメイヴほどひどい目には遭ってないけど、やっぱなんかこれまでの人生で大きく何かを変えられた体験がないし、変えられるというビジョンもない、みたいな...","created":1602315702,"updated":1602315702}]}