{"id":"5fac95f0269cef001e007066","title":"フロントエンドエンジニアがスキルアップのために意識する「素振り」の仕方と求められる役割 | Offers Magazine","image":"https://gyazo.com/a1afad5dc2840b16608aac2dd7d443b6/raw","created":1605146097,"updated":1605146512,"lines":[{"id":"5fac95f0269cef001e007066","text":"フロントエンドエンジニアがスキルアップのために意識する「素振り」の仕方と求められる役割 | Offers Magazine","created":1605146097,"updated":1605146097},{"id":"5fac95f04ade4d0000605b13","text":"[フロントエンドエンジニアがスキルアップのために意識する「素振り」の仕方と求められる役割 | Offers Magazine https://offers.jp/media/sidejob/workstyle/a_1901]","created":1605146097,"updated":1605146097},{"id":"5fac95f04ade4d0000605b14","text":"[https://gyazo.com/a1afad5dc2840b16608aac2dd7d443b6]","created":1605146097,"updated":1605146105},{"id":"5fac95f84ade4d000014fa0b","text":"[Offers Magazine]さんに寄稿しました [[PR]]","created":1605146105,"updated":1605146512},{"id":"5fac96184ade4d000014fa0c","text":"\tインタビュー受けたものを整えて記事化した、という感じなんですが、読み返してみると受け売りのオンパレードで恥ずかしくなっちゃうけど、師たちから受け継いだぞ...!という強い気持ちでそのままいった","created":1605146137,"updated":1605146462},{"id":"5fac95f04ade4d0000605b15","text":"","created":1605146097,"updated":1605146097},{"id":"5fac95f04ade4d0000605b16","text":"","created":1605146097,"updated":1605146097},{"id":"5fac95f04ade4d0000605b17","text":"#20201112 #1112","created":1605146097,"updated":1605146097},{"id":"5fac95f04ade4d0000605b18","text":"","created":1605146097,"updated":1605146097}]}