{"id":"60b3f2ea818c190022ddcdb7","title":"久々に koo さん","image":"https://gyazo.com/101657fce3858bc4f2ec198513a8686a/raw","created":1622405866,"updated":1622405884,"lines":[{"id":"60b3f2ea818c190022ddcdb7","text":"久々に koo さん","created":1622405866,"updated":1622405866},{"id":"60b3f2ea4ade4d0000308b41","text":"from [20210528] #0528","created":1622405866,"updated":1622405872},{"id":"60b3f2ea4ade4d0000308b42","text":"久々に [koo] さん","created":1622405866,"updated":1622405875},{"id":"60b3f2ea4ade4d0000308b43","text":"\t[https://gyazo.com/101657fce3858bc4f2ec198513a8686a]","created":1622405866,"updated":1622405866},{"id":"60b3f2ea4ade4d0000308b44","text":"\t[https://www.youtube.com/watch?v=h1qv4cnWruk]","created":1622405866,"updated":1622405866},{"id":"60b3f2ea4ade4d0000308b45","text":"\t[きおきお]さんて本当に面倒見がいいアニキって感じがするというか、しつこくしつこく声かけしてて偉いなあ、とおもってたらまさかの本人登場でさすがにデカい声でてしまった","created":1622405866,"updated":1622405884}]}