{"id":"62068ff12b0885001d53c0cd","title":"Alchemy - Blockchain API and Node Service | Ethereum, Polygon, Flow, Crypto.org + More","image":"https://gyazo.com/812d81a42e6510fef6f65700da7b7ecb/raw","created":1644597233,"updated":1644597269,"lines":[{"id":"62068ff12b0885001d53c0cd","text":"Alchemy - Blockchain API and Node Service | Ethereum, Polygon, Flow, Crypto.org + More","created":1644597233,"updated":1644597233},{"id":"62068ff14ade4d0000bebafb","text":"[Alchemy - Blockchain API and Node Service | Ethereum, Polygon, Flow, Crypto.org + More https://www.alchemy.com/]","created":1644597233,"updated":1644597233},{"id":"62068ff14ade4d0000bebafc","text":"[https://gyazo.com/812d81a42e6510fef6f65700da7b7ecb]","created":1644597233,"updated":1644597248},{"id":"62068fff4ade4d0000bebb01","text":"[Web3] の足回りやるやつっぽい感じ","created":1644597248,"updated":1644597269},{"id":"62068ff14ade4d0000bebafd","text":"","created":1644597233,"updated":1644597233},{"id":"62068ff14ade4d0000bebafe","text":"","created":1644597233,"updated":1644597233},{"id":"62068ff14ade4d0000bebaff","text":"#20220212 #0212","created":1644597233,"updated":1644597233},{"id":"62068ff14ade4d0000bebb00","text":"","created":1644597233,"updated":1644597233}]}