{"id":"62fa22406e32a9002191f61a","title":"Qualifying Highlights | 2021 Belgian Grand Prix - YouTube","image":"https://i.ytimg.com/vi/E_CvS-dN99Y/mqdefault.jpg","created":1660559937,"updated":1660560184,"lines":[{"id":"62fa22406e32a9002191f61a","text":"Qualifying Highlights | 2021 Belgian Grand Prix - YouTube","created":1660559937,"updated":1660559937},{"id":"62fa22414ade4d0000176a26","text":"[Qualifying Highlights | 2021 Belgian Grand Prix - YouTube https://www.youtube.com/watch?v=E_CvS-dN99Y]","created":1660559937,"updated":1660559937},{"id":"62fa22414ade4d0000176a27","text":"[https://www.youtube.com/watch?v=E_CvS-dN99Y]","created":1660559937,"updated":1660559941},{"id":"62fa22454ade4d0000176a2d","text":"[ノリス]がクラッシュしていたらしいと聞いてみてみたけどまあなかなかひやりとするクラッシュであった...","created":1660559941,"updated":1660560177},{"id":"62fa230b4ade4d0000176a2f","text":"\t[ベッテル]が直後に駆け寄ってて(クルマでだけど)相変わらずこの人は...となった","created":1660560139,"updated":1660560175},{"id":"62fa22414ade4d0000176a28","text":"そして全く知らなかったんだけど、ここで[ラッセル]ポールワンチャンあったんだな","created":1660559937,"updated":1660560181},{"id":"62fa22bd4ade4d0000176a2e","text":"\tこれって移籍決まる前だったのか後だったのか、[メルセデス]がボッタスと入れ替える判断するのもなんかその片鱗が見えた気がした","created":1660560061,"updated":1660560184},{"id":"62fa22414ade4d0000176a29","text":"","created":1660559937,"updated":1660559937},{"id":"62fa22414ade4d0000176a2a","text":"#20220815 #0815","created":1660559937,"updated":1660559937},{"id":"62fa22414ade4d0000176a2b","text":"","created":1660559937,"updated":1660559937},{"id":"62fa22414ade4d0000176a2c","text":"","created":1660559937,"updated":1660559937}]}