{"id":"6329cc1628858f001d1e4135","title":"映画 トロピカル～ジュ！プリキュア 雪のプリンセスと奇跡の指輪！ 感想 (ネタバレあり)","image":null,"created":1663683606,"updated":1663683618,"lines":[{"id":"6329cc1628858f001d1e4135","text":"映画 トロピカル～ジュ！プリキュア 雪のプリンセスと奇跡の指輪！ 感想 (ネタバレあり)","created":1663683606,"updated":1663683606},{"id":"6329cc164ade4d00005919c7","text":"from [20220919] #0919","created":1663683606,"updated":1663683612},{"id":"6329cc164ade4d00005919c8","text":"[映画 トロピカル～ジュ！プリキュア 雪のプリンセスと奇跡の指輪！] 感想 (ネタバレあり)","created":1663683606,"updated":1663683618},{"id":"6329cc164ade4d00005919c9","text":"\t冒頭10分ぐらいで「ああ、[トロプリ]ってこんな感じだったな」と思い出して、放送終了から半年ほどが経って、自分が認識していたよりもこのシリーズのことは好きだったなと思い起こさせてくれた","created":1663683606,"updated":1663683606},{"id":"6329cc164ade4d00005919ca","text":"\t\t4人がけの席におさまらなかったあすかセンパイのために席移動するみのりんセンパイ...","created":1663683606,"updated":1663683606},{"id":"6329cc164ade4d00005919cb","text":"\t話の展開はまあテンプレ感あったけどこんなビターめなオチをつけてくるのかーというのはちょっと驚いた","created":1663683606,"updated":1663683606},{"id":"6329cc164ade4d00005919cc","text":"\t\t国が滅んだとしても文化は遺るみたいなメッセージはよかった","created":1663683606,"updated":1663683606},{"id":"6329cc164ade4d00005919cd","text":"\t\t\tなんとなく[ミノア文明]のことをおもいながらシャンティアをみていた","created":1663683606,"updated":1663683606},{"id":"6329cc164ade4d00005919ce","text":"\t\tでも唄を遺すのって結構難しそう","created":1663683606,"updated":1663683606},{"id":"6329cc164ade4d00005919cf","text":"\t\t\tそもそも我が日本語にしても50年前ぐらいのやつでさえ結構あやしいし","created":1663683606,"updated":1663683606},{"id":"6329cc164ade4d00005919d0","text":"\t\t\tメキシコの文学復興運動みたいなのをちらっと調べた時も大変そうだなと...","created":1663683606,"updated":1663683606},{"id":"6329cc164ade4d00005919d1","text":"\t[くるるん]さんまさかの引き戸を華麗に開けるプレーでシリーズいち輝いた瞬間だったのでは","created":1663683606,"updated":1663683606},{"id":"6329cc164ade4d00005919d2","text":"\t変身は全員フル尺でよかったです","created":1663683606,"updated":1663683606},{"id":"6329cc164ade4d00005919d3","text":"\t\t配信でみたので若干画質怪しかったのが惜しかった...やはり盤を買うしかないのか....","created":1663683606,"updated":1663683606},{"id":"6329cc164ade4d00005919d4","text":"\tなんとなくトロプリと[ハートキャッチ]って絵のテイストが全然違うから、同じフレームの中に違和感なくおさめるの結構むずいのでは？とおもっていたが、そこは[東映アニメーション]パワーでどうにかなっていたのかな","created":1663683606,"updated":1663683606},{"id":"6329cc164ade4d00005919d5","text":"\t\tそしておしりパンチはメガ盛りであった...好きだな......","created":1663683606,"updated":1663683606},{"id":"6329cc164ade4d00005919d6","text":"\tえりかに対するつぼみをローラに対するまなつに当ててきたのはグッときてしまった","created":1663683606,"updated":1663683606},{"id":"6329cc164ade4d00005919d7","text":"\tエンディングは公開当時に映画の ED がそのまま本編の ED になってて「芽吹く春 真夏の太陽」のパンチラインの部分だけでこみあげてくるものがあり、やばかったのを思い出した","created":1663683606,"updated":1663683606},{"id":"6329cc164ade4d00005919d8","text":"\tおまけ映像で[デパプリ]映画の併映作品に出ている3人の鼎談が入ってたけど、この改めてスターは[えいたそ]センパイのあてがきだったんじゃないかというくらいそのままでグッときてしまう","created":1663683606,"updated":1663683606},{"id":"6329cc164ade4d00005919d9","text":"\tこの機会にちょっと[トロプリ]を(主にくるるんさんの出番だけ)見返してたんだけど、冷静に考えると[ポルナレフ]と[徐倫]が戦ってて笑ってしまった","created":1663683606,"updated":1663683606},{"id":"6329cc164ade4d00005919da","text":"","created":1663683606,"updated":1663683606}]}