{"id":"634e628ae91ba00020ca95f6","title":"20221018","image":null,"created":1666081421,"updated":1666103315,"lines":[{"id":"634e628ae91ba00020ca95f6","text":"20221018","created":1666081421,"updated":1666081421},{"id":"634e628c4ade4d00000b4b31","text":"#1018","created":1666081421,"updated":1666081425},{"id":"634e62914ade4d00000b4b33","text":"","created":1666081426,"updated":1666081426},{"id":"634ea3ab4ade4d0000d857a4","text":"第二次香り戦争","created":1666098091,"updated":1666098098},{"id":"634ea3b34ade4d0000d857a6","text":"\t第一次は、一時的かとおもっていた在宅ワークが「これは長引くぞ」と確信した時にはじまった","created":1666098099,"updated":1666098169},{"id":"634ea3f94ade4d0000d857a7","text":"\tずっと家にいるので、イイ匂いの中で仕事できるのでは？と","created":1666098169,"updated":1666098185},{"id":"634ea4094ade4d0000d857a8","text":"\t適当に精油を買っては混ぜたりなんだりして、最終的に[ユーカリ]と[ティーツリー]をベースにあとはトップを気分に合わせて変えよ〜みたいな感じで仕上がった","created":1666098185,"updated":1666103074},{"id":"634eb5b34ade4d0000d857a9","text":"\t夏場は湿度がヤベエので -TOKYO JUNGLE- 何も焚いてなかったが、そろそろシーズンかなと","created":1666102707,"updated":1666102751},{"id":"634eb5df4ade4d0000d857aa","text":"\t[香水]の[サブスク]みたいなやつを認識したのだが、やっぱりこういう物理が絡むサブスクって結局実物を買うのとどっちが得なの？て話になってしまう","created":1666102751,"updated":1666102854},{"id":"634eb6474ade4d0000d857ab","text":"\tで、こういうサブスクでは、高級な香水は容量多くてそんなに使いきれねーYO!というところがペインポイントらしく、高級な香水を少量試せるのでよいということらしい","created":1666102855,"updated":1666102939},{"id":"634eb69e4ade4d0000d857ac","text":"\tじゃあ高級な香水ってどんな香りなのよ？という話なんだが、こと匂いに関してはインターネットの情報が全く役に立たず、何がなんやらさっぱり分からんということで実物を嗅ぎに行くことに","created":1666102942,"updated":1666102984},{"id":"634eb6c94ade4d0000d857ad","text":"\tデカモールで適当に物色して、結局のところユーカリが好きだということを再認識しただけだった","created":1666102985,"updated":1666103009},{"id":"634eb6e14ade4d0000d857ae","text":"\t\t[ヒノキ]や[ヒバ]が良かったので、これは精油で買おうかな、みたいな","created":1666103010,"updated":1666103045},{"id":"634eb7084ade4d0000d857af","text":"\t\t\t(結局木かよ!!)","created":1666103049,"updated":1666103056},{"id":"634eb7114ade4d0000d857b0","text":"\t\tあとオッサン向けの高級な香水は「うわ！このオジサンの臭い知ってる！！！」みたいな感じになった","created":1666103057,"updated":1666103105},{"id":"634eb7434ade4d0000d857b1","text":"\t発見だったのは [SABON] の「[パチュリ]・[ラベンダー]・[バニラ]」てやつで、バニラってもっと甘ったるい感じの印象だったんだけど、この組み合わせがいいのかなんなのか、落ち着いた雰囲気で良し","created":1666103108,"updated":1666103246},{"id":"634eb7d24ade4d0000d857b2","text":"\t部屋はユーカリでいいやってことで[シャワーオイル]を買った","created":1666103250,"updated":1666103291},{"id":"634eb7fc4ade4d0000d857b3","text":"\t\t泡立てる時に脳天を突く香りが湧き上がってすげかった(こなみかん)","created":1666103292,"updated":1666103315},{"id":"634ea3ab4ade4d0000d857a5","text":"","created":1666098091,"updated":1666098091},{"id":"634e62924ade4d00000b4b34","text":"[二つと十億のアラベスク] Audible 版 感想 (ネタバレあり)","created":1666081426,"updated":1666087429},{"id":"634e62b54ade4d00000b4b35","text":" これは果たして望むべき結末だったのだろうか…？","created":1666081461,"updated":1666081897},{"id":"634e646a4ade4d00000b4b36","text":" 中盤から人間と人工知能の同性愛という[SF百合]っぽい展開に少々驚いたが、バックグラウンドとなる世界は、そもそもこれは人間の望む未来なのか…？と不安になる描写が多々あり、なんとも言えない気分になった","created":1666081899,"updated":1666087436},{"id":"634e64dd4ade4d00000b4b37","text":" 　現在からして、人工知能とまでは言わずとも、ある程度のアルゴリズムに従って意思決定をすることは現代を生きる者としては当然日常的に行なっていることではあるのだが、果たしてその俎上に挙げられた選択肢が恣意的に手が加わっているとしたら…？恐ろしくなる","created":1666082013,"updated":1666082112},{"id":"634e65474ade4d00000b4b38","text":" 　上級インターフェースであるタカセが人間が好むような仕草をすることをユイは自覚しつつも、それに惹かれてしまっているあたりなんていうか、ECでレコメンドされるがままに商品を買ってしまうとか、動画配信サービスでレコメンドされるがままに作品をみてしまうとか、そういうことってもう既にある感じがする","created":1666082119,"updated":1666087490},{"id":"634e7a424ade4d0000d408b9","text":" 2つ曲のバリエーションがあるならそこそこ筋立ててどっちはどうっていうジャッジはできるけど、10億種類の曲があったら果たして人間は有限時間中に選択できるのだろうか？というのが核心的な問いで、それについて[人工知能]なり[アルゴリズム]なりが枝刈りをして提示してきた選択肢に意図は本当にないのだろうか？","created":1666087491,"updated":1666087638},{"id":"634e7ad94ade4d0000d408ba","text":" \tちょうど最近 [txt2img] や [img2img] をやるいろいろが流行っているけど、そのモデルや元データの扱いについては賛否両論といった感じがする","created":1666087641,"updated":1666087718},{"id":"634e7b2a4ade4d0000d408bb","text":" \tそしてモデルに対して筋立てて説明できる人間がいるんだろうか？自分はそんなに詳しいわけではないが、あの界隈は「なんかわからんけど動く」を地でやっていると認識している","created":1666087723,"updated":1666087782},{"id":"634e7b6c4ade4d0000d408bc","text":" \t\t10億(もしくはもっと)の画像のバリエーションの中から最適っぽいのをアルゴリズムに引いてきてもらっている状態なのではないだろうか","created":1666087788,"updated":1666087901},{"id":"634e7be64ade4d0000d408bd","text":" 現状まだそこまで介入されている感は薄いけど(実は認識している以上に食い込まれているんだろうか？)、例えば [GitHub Copilot] がもっと普及してきて、[TypeScript] がもはや[インテリセンス]がないと書けないように、Copilot のアシストなしでは複雑なアルゴリズムを表現できなくなってしまったりするんだろうか？","created":1666087910,"updated":1666088016},{"id":"634e7c574ade4d0000d408be","text":" \tそうなった時に、自分が Copilot を経由して書くコードにどれほどの価値があるんだろう？","created":1666088023,"updated":1666088057},{"id":"634e7c7a4ade4d0000d408bf","text":" \t作中でも[ベーシックインカム]などが実現した世界は、実はひどく退屈であるという様子が伝わってくるが、そんな社会が実現した時に \"人間にしかできない\" 創作的な作業に没頭できたりするんだろうか？","created":1666088059,"updated":1666088220},{"id":"634e7d2f4ade4d0000d408c0","text":" \t\tそして現実では \"人間にしかできない\" とおもわれていそうな領域から食われていっている感じがする","created":1666088239,"updated":1666088894},{"id":"634e7fbe4ade4d0000d408c1","text":" \t\tそうなると完全にディストピアっぽいけど、機械に置き換えるにはコストがかかりすぎる領域(人間にやらせた方が安上がり)にだけ人間が残されて、コスパがいい領域は機械にとって代わられるということに....","created":1666088895,"updated":1666089099},{"id":"634e80914ade4d0000d408c2","text":" 途中、ミナトが実は人間に紛れた人工知能なのではないかとヒヤっとしたが、さすがにそれは違ったっぽい","created":1666089105,"updated":1666089144},{"id":"634e62914ade4d00000b4b32","text":"","created":1666081425,"updated":1666081425}]}