{"id":"643e3c6a9afea1001be27bcb","title":"Go!プリンセスプリキュア 39話 感想 (ネタバレあり)","image":null,"created":1681800299,"updated":1681800370,"lines":[{"id":"643e3c6a9afea1001be27bcb","text":"Go!プリンセスプリキュア 39話 感想 (ネタバレあり)","created":1681800299,"updated":1681800299},{"id":"643e3c6b4ade4d0000af3af3","text":"from [20230413] #0413","created":1681800299,"updated":1681800303},{"id":"643e3c6b4ade4d0000af3af4","text":"[Go!プリンセスプリキュア] 39話 感想 (ネタバレあり)","created":1681800299,"updated":1681800299},{"id":"643e3c6b4ade4d0000af3af5","text":"\t[Go!プリンセスプリキュア 38話 感想 (ネタバレあり)]の負け表現がかなりよくて、果たしてこっからどうやってカムバックしてくるのかなあ？と期待8割、不安2割みたいな...","created":1681800299,"updated":1681800299},{"id":"643e3c6b4ade4d0000af3af6","text":"\t39話も前半パートはよくて、はるはるにも多少は気持ちが残ってて、現場に向かうんだけど[ドレスアップキー]をカチャカチャしても変身できない描写とか、モノクロになったシリーズロゴで CM に暗転したりと絶望描写はかなり良かった","created":1681800299,"updated":1681800299},{"id":"643e3c6b4ade4d0000af3af7","text":"\tただ、立ち直り方がピンとこなくて、子供の頃の初期衝動を思い出して戻れた...?という解釈でいいのかなあ？","created":1681800299,"updated":1681800299},{"id":"643e3c6b4ade4d0000af3af8","text":"\t\t子供の頃のなりたい自分になるためというか、子供の頃の自分を救うための今みたいなこと...?","created":1681800299,"updated":1681800299},{"id":"643e3c6b4ade4d0000af3af9","text":"\tみなみさんやきららさんやゆいぴょんとやりとりするわけでもなく、内省で再び立ち上がるってのはうーん.....ちょっと消化不良","created":1681800299,"updated":1681800299},{"id":"643e3c6b4ade4d0000af3afa","text":"\t\tしかもそういうはるはるをみて記憶が戻ったぞ〜いのカナタってのもなんかご都合主義的というかなんというか....","created":1681800299,"updated":1681800299},{"id":"643e3c6b4ade4d0000af3afb","text":"\t\t\tなんとなく記憶喪失状態のカナタをここで[ホープキングダム]の王族に戻しちゃうのはもったいない気がする","created":1681800299,"updated":1681800299},{"id":"643e3c6b4ade4d0000af3afc","text":"\t\t\t\tカナタには市井の人として[バイオリン]作りをやりながら暮らしてて、それでも己からにじみ出る何かでもって[プリキュア]に助太刀する...みたいな展開とかアツくない？とか","created":1681800299,"updated":1681800370},{"id":"643e3c6b4ade4d0000af3afd","text":"\t\t\t\tトワに対してやったことの二番煎じになるかもだけど、あの冒頭の構図を反転させて落ち込んでるカナタにはるはるが何かを託すとかさ","created":1681800299,"updated":1681800299},{"id":"643e3c6b4ade4d0000af3afe","text":"\t自分が問題提起を感じ取りすぎなのかもしれんが","created":1681800299,"updated":1681800299},{"id":"643e3c6b4ade4d0000af3aff","text":"\tまあひとまず最終盤に向けて、新合体技も登場したし、目下気になるのはみなみさんの身の処し方だなあ","created":1681800299,"updated":1681800299},{"id":"643e3c6b4ade4d0000af3b00","text":"\t\t我道を往く海洋生物学者的な人と出会って何かがスパークしたようだったけど...","created":1681800299,"updated":1681800299},{"id":"643e3c6b4ade4d0000af3b01","text":"\t\tあと38話で並んで歩いてたとこでスッ....てフレームアウトしていくのとかフリですよね？","created":1681800299,"updated":1681800299},{"id":"643e3c6b4ade4d0000af3b02","text":"\tトワもある意味家業を継ぐ人だし、みなみ、きらら両氏も2世なので、家業の和菓子屋を継ぐわけでもなく夢に向かってるのははるはるだけって構成で、みなみさんはレールから外れることにまあカタルシスがあるかもしれないけど、そうするときららさんとかちょっと無邪気すぎません？にみえそうな気もする","created":1681800299,"updated":1681800299},{"id":"643e3c6b4ade4d0000af3b03","text":"\t\tかといってみんな反抗するのがいいわけでもないだろうしなあ","created":1681800299,"updated":1681800299},{"id":"643e3c6b4ade4d0000af3b04","text":"","created":1681800299,"updated":1681800299}]}