{"id":"64576026ca138a7ce003b7f5","title":"20230507","image":null,"created":1683447849,"updated":1683563069,"lines":[{"id":"64576026ca138a7ce003b7f5","text":"20230507","created":1683447849,"updated":1683447849},{"id":"645760284ade4d0000af42f4","text":"#0507","created":1683447849,"updated":1683447849},{"id":"645760284ade4d0000af42f5","text":"","created":1683447849,"updated":1683447849},{"id":"6457ea9c4ade4d000090bab7","text":"[Apex Legends その1]","created":1683483292,"updated":1683562904},{"id":"6457ebd14ade4d000090bac2","text":"","created":1683483600,"updated":1683483600},{"id":"6457ebc24ade4d000090bac1","text":"\t","created":1683483586,"updated":1683483586},{"id":"6457ea9c4ade4d000090bab8","text":"","created":1683483292,"updated":1683483292},{"id":"6457e85e4ade4d000090baaa","text":"[ひろプリ 14話 感想 (ネタバレあり)]","created":1683482718,"updated":1683562919},{"id":"6457e85f4ade4d000090baab","text":"","created":1683482718,"updated":1683482718},{"id":"6457e5064ade4d0000eb0b86","text":"[ダンス100 準決勝 感想 (ネタバレあり)]","created":1683481862,"updated":1683562979},{"id":"6457e5074ade4d0000eb0b87","text":"","created":1683481862,"updated":1683481862},{"id":"64576c404ade4d0000af4302","text":"https://zenn.dev/uhyo/articles/react-server-components-multi-stage","created":1683450945,"updated":1683450946},{"id":"64576c424ade4d0000af4304","text":"\t[Next.js] どんどんわからなくなっていってるなーと....","created":1683450947,"updated":1683450970},{"id":"64576c6a4ade4d0000af4305","text":"\t\tNext on Rails とか [PHP] とかイロイロ言われてるけどそれはそうだな感","created":1683450987,"updated":1683451027},{"id":"64576ca84ade4d0000af4306","text":"\tいわゆるサーバ的な機能と[ブラウザ]で動くアプリケーションは分離したいタチなのでなんでもかんでも next ってのはなあ....と","created":1683451049,"updated":1683451134},{"id":"64576cfe4ade4d0000af4307","text":"\t\t[CRA] よりも簡易に立ち上がる [react] 環境として next はイイとおもってたけど、最近は [vite] ベースのなんらかの方がよくみえる","created":1683451135,"updated":1683451186},{"id":"64576d324ade4d0000af4308","text":"\t\t\t[RSC] とかいらんし....","created":1683451187,"updated":1683451194},{"id":"64576c414ade4d0000af4303","text":"","created":1683450945,"updated":1683450945},{"id":"6457602a4ade4d0000af42f6","text":"[Archivebox で UA 変更]","created":1683447850,"updated":1683563069},{"id":"6457602a4ade4d0000af42f7","text":"","created":1683447850,"updated":1683447850}]}