{"id":"64bf6569434f92001b009559","title":"それって魔法かも？ | Negicco","image":null,"created":1690264938,"updated":1690264942,"lines":[{"id":"64bf6569434f92001b009559","text":"それって魔法かも？ | Negicco","created":1690264938,"updated":1690264938},{"id":"64bf65694ade4d00009009e8","text":"from [20230724] #0724","created":1690264938,"updated":1690264942},{"id":"64bf65694ade4d00009009e9","text":"[それって魔法かも？ | Negicco]","created":1690264938,"updated":1690264938},{"id":"64bf65694ade4d00009009ea","text":"\t[https://open.spotify.com/album/0PROBHvZSqDRB1XEMj2IxC?si=OE7uWQbSTeycy7UUckbbKw]","created":1690264938,"updated":1690264938},{"id":"64bf65694ade4d00009009eb","text":"\t[Negicco]","created":1690264938,"updated":1690264938},{"id":"64bf65694ade4d00009009ec","text":"","created":1690264938,"updated":1690264938}]}