{"id":"662a15da8f6ac90026cf0ad5","title":"AirPods Pro のイヤーチップを換装","image":null,"created":1714034139,"updated":1721568349,"lines":[{"id":"662a15da8f6ac90026cf0ad5","text":"AirPods Pro のイヤーチップを換装","created":1714034139,"updated":1714034139},{"id":"662a15db4ade4d000065d734","text":"from [20240422] #0422","created":1714034139,"updated":1714034144},{"id":"662a15db4ade4d000065d735","text":"[AirPods Pro] のイヤーチップを換装","created":1714034139,"updated":1714034139},{"id":"662a15db4ade4d000065d736","text":"\t買った時に Ear Fit Test 的なやつをやって OK! みたいになったので、特に気にしていなかったのだけど何気なく妻に「こう、上から見下ろす角度みたいな時に保持しきれなくなって落っこちることがあって〜」と話たら「それはイヤーチップ変えなよ」と指摘され、いやその発想はなかったわ....と","created":1714034139,"updated":1714034139},{"id":"662a15db4ade4d000065d737","text":"\t\t装着されているイヤーチップのサイズが根本に書いてあるよとのことだったので確認してみると M だった","created":1714034139,"updated":1714034139},{"id":"662a15db4ade4d000065d738","text":"\t\tAirPods の箱を引っ張り出してきて確認してみると L のイヤーチップが同梱されていて、試しに装着してみたらかなりフィット感が良くなり、遮音性もあがった気がする","created":1714034139,"updated":1714034139},{"id":"662a15db4ade4d000065d739","text":"\t\t\tAirPods のノイキャン性能みんな褒めてるけど、そこまでか....??とおもっていたがフルパワーじゃなかった模様","created":1714034139,"updated":1714034139},{"id":"662a15db4ade4d000065d73a","text":"\t\tこの人と[結婚してよかった]〜〜〜....(そこで?)となった","created":1714034139,"updated":1721568349},{"id":"662a15db4ade4d000065d73b","text":"\tしばらく L で試してみる","created":1714034139,"updated":1714034139},{"id":"662a15db4ade4d000065d73c","text":"","created":1714034139,"updated":1714034139}]}