{"id":"66bae45db58649001c67edfe","title":"20240813","image":null,"created":1723524192,"updated":1723627796,"lines":[{"id":"66bae45db58649001c67edfe","text":"20240813","created":1723524192,"updated":1723524192},{"id":"66bae45f4ade4d0000229234","text":"#0813","created":1723524192,"updated":1723524197},{"id":"66bae45f4ade4d0000229235","text":"","created":1723524192,"updated":1723524192},{"id":"66bb42e24ade4d0000229250","text":"[学マス  倉本千奈 A+編 感想 (ネタバレあり)]","created":1723548387,"updated":1723627778},{"id":"66bb47474ade4d0000229277","text":"\t","created":1723549512,"updated":1723549512},{"id":"66bb453e4ade4d0000229265","text":"\t","created":1723548990,"updated":1723548990},{"id":"66bb43154ade4d0000229254","text":"","created":1723548438,"updated":1723548438},{"id":"66bb43154ade4d0000229255","text":"","created":1723548438,"updated":1723548438},{"id":"66bb42e24ade4d0000229251","text":"","created":1723548387,"updated":1723548387},{"id":"66bb3fc84ade4d000022923e","text":"[学マス  初星コミュ 第二章 Vol.3 1日め 感想 (ネタバレあり)]","created":1723547593,"updated":1723627796},{"id":"66bb46664ade4d0000229272","text":"\t","created":1723549287,"updated":1723549287},{"id":"66bb454c4ade4d0000229268","text":"\t","created":1723549004,"updated":1723549004},{"id":"66bb3fc84ade4d000022923f","text":"","created":1723547593,"updated":1723547593},{"id":"66bb3fc84ade4d0000229240","text":"","created":1723547593,"updated":1723547593},{"id":"66bae4df4ade4d000022923d","text":"https://note.com/gotch_akg/n/n74103eba8d14","created":1723524319,"updated":1723524319},{"id":"66bae4604ade4d0000229236","text":">彼女たちはいつも「ナメられてたまるか」とファイティングポーズを取っていたように感じる。それは、もう本当に、俺もその一部で反省し続けているけれど、音楽業界が男性優位の社会だからだと思う。クソのようなアドバイスというか、[マンスプレイニング]みたいな態度や慣習と戦い続けながら、[音楽]では決してそう見せないところが格好良かった。","created":1723524192,"updated":1723524349},{"id":"66bae4a54ade4d0000229239","text":">(中略)","created":1723524261,"updated":1723524264},{"id":"66bae4a94ade4d000022923a","text":">そんなものと戦うことにエネルギーを割かなければいけないことは損失だと思う。","created":1723524265,"updated":1723524266},{"id":"66bae4ce4ade4d000022923b","text":">(中略)","created":1723524303,"updated":1723524307},{"id":"66bae4d34ade4d000022923c","text":">現在や将来にチャットモンチーのようなバンドが新しく生まれてくるならば、[おっさんたちが偉そうに踏ん反りかえるような場所]は絶滅させて、世界の果てまで突き抜けられるような環境を大人のひとりとして用意したい。そういう努力は死ぬまで続けたいと思う。","created":1723524307,"updated":1723524368},{"id":"66bae4604ade4d0000229237","text":"","created":1723524192,"updated":1723524335},{"id":"66bae4604ade4d0000229238","text":"","created":1723524192,"updated":1723524192}]}