{"id":"66dfc0067be6a9001c45c914","title":"20240910","image":"https://gyazo.com/fdfdde2964456f813ec03041b345d858/raw","created":1725939722,"updated":1725987670,"lines":[{"id":"66dfc0067be6a9001c45c914","text":"20240910","created":1725939722,"updated":1725939722},{"id":"66dfc0094ade4d0000393a75","text":"#0910","created":1725939722,"updated":1725939722},{"id":"66dfc0094ade4d0000393a76","text":"","created":1725939722,"updated":1725939722},{"id":"66e0711a4ade4d0000393a8f","text":"[学マス] [葛城リーリヤ] A+ 編 感想 (ネタバレあり)","created":1725985051,"updated":1725985070},{"id":"66e0712f4ade4d0000393a92","text":"\t[https://gyazo.com/fdfdde2964456f813ec03041b345d858]","created":1725985071,"updated":1725985099},{"id":"66e0714a4ade4d0000393a93","text":"\t10話.....ッ!! よかった.....ッ!!!!","created":1725985099,"updated":1725985116},{"id":"66e0715e4ade4d0000393a94","text":"\tこれ、デュオの結成譚としちゃあベタっちゃベタだけど、この王道感が最高....ッ!!","created":1725985118,"updated":1725985149},{"id":"66e0717f4ade4d0000393a95","text":"\t\tプロデューサーことオレとならじゃなくて[紫雲清夏]と2人ならどこまでだっていけるぜ....の方がアツかったが、そこは脳内補正しました","created":1725985152,"updated":1725985222},{"id":"66e071c94ade4d0000393a96","text":"\t[初星コミュ]ぐらいのボリュームでタッグ編やってくれ〜〜〜〜〜頼む〜〜〜〜〜〜あとデュオ曲〜〜〜〜〜頼む〜〜〜〜〜〜〜〜〜〜","created":1725985226,"updated":1725985263},{"id":"66e071f04ade4d0000393a97","text":"\t[https://gyazo.com/df7d22f375af38f9536eb608326df04f]","created":1725985264,"updated":1725985295},{"id":"66e0720f4ade4d0000393a98","text":"\t相変わらず休み育成OTPやってる","created":1725985295,"updated":1725985306},{"id":"66e0721f4ade4d0000393a99","text":"\tレベル上がって、[虹色ドリーマー]がピックできるようになって、これは[好印象]組にかなりドリームを感じた","created":1725985311,"updated":1725985369},{"id":"66e0725b4ade4d0000393a9a","text":"\t\t最初は[冠菊 藤田ことね]と合わせてたんだけど、[冠菊 花海咲季]にも合わせてみて「コレはいけるな」と","created":1725985371,"updated":1725985431},{"id":"66e0729a4ade4d0000393a9b","text":"\t\tところで、葛城さんは [SR] しか持ってなくて、SR はアイテムもカードも貧弱なのだが、これをドリームと休みでメイクチャンスしようという作戦","created":1725985435,"updated":1725987670},{"id":"66e072c94ade4d0000393a9c","text":"\t[https://gyazo.com/9f95747c22bd59c640847df1e6b841fe]","created":1725985482,"updated":1725985506},{"id":"66e072e14ade4d0000393a9d","text":"\tカードはこんな感じで、差分はといえばドリームぐらいで、あとは[トキメキ]をいれたぐらいかな","created":1725985506,"updated":1725985557},{"id":"66e073164ade4d0000393a9e","text":"\t\t休み育成のつもりだったんだけど、好印象は体力を減らすのが逆にムズくて、道中が安定して安定して仕方なくて、しゃーなしで相談を選ぶハメになったりしたが形にはなった","created":1725985558,"updated":1725985617},{"id":"66e073534ade4d0000393aa0","text":"\t\t[やる気]型偏重でやってるので、やる気があまりに道中ギャンブルすぎて、最終ステータスの伸びはいいけど失敗するととことんうまくいかないので安定してメモリーを作るって意味では好印象も悪くないんかなとおもったりはした","created":1725985620,"updated":1725985689},{"id":"66e0739a4ade4d0000393aa1","text":"\t\tつーても、最終試験は何ターンめにドリームがくるかの勝負みたいなフシがあって、3ターンあたりかな？でドリーム引けてガッツポーズした","created":1725985691,"updated":1725985736},{"id":"66e073c84ade4d0000393aa2","text":"\t[https://gyazo.com/9bb6a9fa5504b00da4e899381c609cf3]","created":1725985737,"updated":1725985749},{"id":"66e073d44ade4d0000393aa3","text":"\t[倉本千奈]がセンセイと呼んでくるのと同様に、センパイと呼んでくるのがやや居心地が悪くて後回しにしていたフシがあったのだが.....こんなエェ10話用意してくれているんだったらもっと急いでもよかったかもしれん","created":1725985749,"updated":1725985940},{"id":"66e074834ade4d0000393aa5","text":"\t\tつーてもドリーム待ちだったわけだけど...","created":1725985923,"updated":1725985942},{"id":"66e0748a4ade4d0000393aa6","text":"\tで.....やや毎度恒例になりつつある「いや〜、さすがにもう [Campus mode!!] 把握したんで、自分大丈夫ッス！」からの〜〜のやつをまたやってしまった","created":1725985931,"updated":1725986052},{"id":"66e075664ade4d0000393aa9","text":"\t\t>そう君が勇気をさ 元気をさ くれたんだよ","created":1725986150,"updated":1725986165},{"id":"66e075054ade4d0000393aa7","text":"\t\t>「できる」って叫ぼう　「できる」って笑おう","created":1725986053,"updated":1725986089},{"id":"66e075284ade4d0000393aa8","text":"\t\t....コレ、今までのキャラクターだと自分自身に対するラインだという受け止めだったけど、葛城編でこのラインは紫雲へのメッセージに聞こえる！！！！！！！！","created":1725986089,"updated":1725986285},{"id":"66e0757c4ade4d0000393aab","text":"\t\tSR だったのもあって、ライブは「[初]」だったわけだけども、何曲かやったと仮定して(←??) Campus mode!! も披露してて、それを紫雲が客席側で聞いてたとしたらそんなん泣いちゃうって！！！！！！！！てかオレが泣く！！！！！！！！！！(←??)","created":1725986172,"updated":1725986311},{"id":"66e073474ade4d0000393a9f","text":"\t10話でウルウルしてたところを Campus mode!! で粉砕されてしまった、号泣メーン","created":1725985607,"updated":1725986354},{"id":"66e076324ade4d0000393aac","text":"\t[https://gyazo.com/b8fefbb3d3c145a4df7479c4f05bd27b]","created":1725986354,"updated":1725986370},{"id":"66e076424ade4d0000393aad","text":"\tシナリオは[雨宮和希]さん","created":1725986370,"updated":1725986386},{"id":"66e076544ade4d0000393aae","text":"\t\tありがとうありがとう.....","created":1725986388,"updated":1725986393},{"id":"66e0766e4ade4d0000393aaf","text":"\tこれで残すはあと1人、[紫雲清夏]サマ.....!","created":1725986414,"updated":1725986469},{"id":"66e076854ade4d0000393ab0","text":"\t\tもしかして葛城-紫雲シナリオが雨宮さんだったりするのかな？","created":1725986437,"updated":1725986457},{"id":"66e076994ade4d0000393ab1","text":"\t\tフラワーは貯まってて、交換すれば [SSR] [紫雲清夏]を解放できるんだけども、あまりにも[セミブルー] [紫雲清夏]が強そうすぎて.....","created":1725986458,"updated":1725986627},{"id":"66e077424ade4d0000393ab2","text":"\t\t\tこれ解放する手段今後実装されたりするのかなあ","created":1725986627,"updated":1725986646},{"id":"66e077624ade4d0000393ab3","text":"","created":1725986659,"updated":1725986659},{"id":"66e077624ade4d0000393ab4","text":"","created":1725986659,"updated":1725986659},{"id":"66e077634ade4d0000393ab5","text":"\t週報","created":1725986659,"updated":1725986663},{"id":"66e077674ade4d0000393ab6","text":"\t[https://gyazo.com/bed92e7162d513a450698e4c95b2db89]","created":1725986664,"updated":1725986817},{"id":"66e078014ade4d0000393ab7","text":"\tティー&ティー&コーヒーとかいうとんでも上振れドリンク引きの回","created":1725986817,"updated":1725986862},{"id":"66e0782f4ade4d0000393ab8","text":"\t[https://gyazo.com/d597db87cf034fa70cd7a265af292ddc]","created":1725986863,"updated":1725986884},{"id":"66e078444ade4d0000393ab9","text":"\t地道にメモリーづくりを頑張ってて、や〜〜〜〜〜っと[届いて！]込みメモリーを作れたので[アイドルの道]を進めている様子","created":1725986884,"updated":1725986933},{"id":"66e078774ade4d0000393aba","text":"\t[https://gyazo.com/9d44681a56d1dc1689e2b03ac04f53a0]","created":1725986936,"updated":1725986952},{"id":"66e078884ade4d0000393abb","text":"\tコンテスト向けも兼ねて、[篠澤広]などのキャラクターもこつこつやってたらついに[届いて！]を自作できた回","created":1725986952,"updated":1725986998},{"id":"66e07b044ade4d0000393ac8","text":"\t\tここまでレンタルするしかなくて、日に3回しかチャンスがなくて厳しかった","created":1725987589,"updated":1725987603},{"id":"66e07b144ade4d0000393ac9","text":"\t\t次はドリームや...","created":1725987604,"updated":1725987608},{"id":"66e078b54ade4d0000393abc","text":"\t[https://gyazo.com/d4d5d7fd8b1d0daede7b2bfec139749a]","created":1725986998,"updated":1725987012},{"id":"66e078c34ade4d0000393abd","text":"\t前シーズンは207位でフィニッシュ、無事昇格","created":1725987012,"updated":1725987036},{"id":"66e078dd4ade4d0000393abe","text":"\t\tここまで順当にボーダーより上を維持していたのだが、グレ5の人々明らかに強くなってる感じがする....","created":1725987038,"updated":1725987071},{"id":"66e078ff4ade4d0000393abf","text":"\t\t日に3,4勝は堅かったんだけど、素で1勝で終わりの日とかあってキツイ","created":1725987071,"updated":1725987102},{"id":"66e0791f4ade4d0000393ac0","text":"\t\t[やる気]多めの構成なんだけど、さすがにコンテストだとギャンブルすぎるのかなあ","created":1725987104,"updated":1725987123},{"id":"66e079354ade4d0000393ac1","text":"\t[https://gyazo.com/96a990d8963d5eaf88b4b4d2dfba810d]","created":1725987125,"updated":1725987152},{"id":"66e079504ade4d0000393ac2","text":"\t素材もあるしな〜〜ってことで、一番キャラパワーがありそうな篠澤さんを2人めの特訓6の人とした","created":1725987152,"updated":1725987185},{"id":"66e079734ade4d0000393ac3","text":"\t\tやる気型の永遠の課題として、[元気]を積むだけ積んで、最終ターンで得点カードが引けないって弱点を、アイテムで最低限は回収してくれるって保証つきなのは強いとおもう","created":1725987187,"updated":1725987253},{"id":"66e079b84ade4d0000393ac4","text":"\t[ロジック]組は割と仕上がってきた感じがするんだけど、[センス]組どうしたもんかなあ....","created":1725987256,"updated":1725987304},{"id":"66e079e94ade4d0000393ac5","text":"\t\tマジでスケールのさせ方がワカラン....","created":1725987305,"updated":1725987395},{"id":"66e07a504ade4d0000393ac6","text":"\t\tなるべく[集中]と[好調]積んで[絶好調]でキメるしかないんだろうけど、全然安定しないんだよな〜....あと素朴に元気がスケールしづらくて、体力がキツい","created":1725987408,"updated":1725987455},{"id":"66e07a8f4ade4d0000393ac7","text":"\t\t\t[バズワード]とかめちゃめちゃ重いし....","created":1725987472,"updated":1725987481},{"id":"66e0711a4ade4d0000393a90","text":"","created":1725985051,"updated":1725985051},{"id":"66e0711a4ade4d0000393a91","text":"","created":1725985051,"updated":1725985051},{"id":"66e0556a4ade4d0000393a81","text":"[LCK] 2024 Summer Split","created":1725977963,"updated":1725977975},{"id":"66e055794ade4d0000393a83","text":"\tレギュラーシーズンはチーム数が多いのでダイジェストとかでつまみ食いでみてたんだけど、プレーオフからずっと面白かったな〜〜〜〜","created":1725977978,"updated":1725978013},{"id":"66e0559d4ade4d0000393a85","text":"\tとはいえ一番面白かったのは決勝で、正直このカードで3-0されてる [HLE] だったのでさすがにあって3-1だよなあ....とおもってたらまさかの2-2までもつれ込んで、最終試合で [GEN] の先出し[コーキ]にオレですら ??? になった","created":1725978014,"updated":1725978105},{"id":"66e055fa4ade4d0000393a86","text":"\t\tなんか [EWC] の時もそうだったけど GEN てここ一番に弱いんか？","created":1725978106,"updated":1725978137},{"id":"66e0561c4ade4d0000393a87","text":"\t\tレギュラーシーズンこんだけドミネートして、HLE も最初は3-0でボコってたのに決勝で負けることあるんや....","created":1725978140,"updated":1725978174},{"id":"66e056914ade4d0000393a89","text":"\t\t最初の試合が響いた感じがしたなあ、最初の試合はいつもの GEN って感じで勝てそうな雰囲気だったのにあそこ落としたのが本当に痛すぎたな....","created":1725978257,"updated":1725978293},{"id":"66e0565a4ade4d0000393a88","text":"\t終わってみればなんか [Zeka] の物語だったんだな、散々タコられて [Chovy] に向き合い続けてついにここ一番で勝ちを拾ったわけだからなあ....","created":1725978202,"updated":1725978255},{"id":"66e057474ade4d0000393a8d","text":"\t\tとはいえ負けてる試合でも [Chovy] はミクロでは勝ってた感じしたな","created":1725978440,"updated":1725978461},{"id":"66e057644ade4d0000393a8e","text":"\t\t[スモルダー]ってあんな早くスタック貯まるんや、っていう","created":1725978468,"updated":1725978485},{"id":"66e056c84ade4d0000393a8a","text":"\t[Worlds 2024] も GEN が他リージョンとどんな試合をするのか楽しみにしてたけど、HLE もかなり強いやろコレ","created":1725978313,"updated":1725978364},{"id":"66e056fc4ade4d0000393a8b","text":"\t\t準決勝で [T1] をボコってて、これは T1 のオウンゴール的な負けなんかとおもったけど HLE も相当安定して強い感じがした","created":1725978365,"updated":1725978401},{"id":"66e057294ade4d0000393a8c","text":"\t\t","created":1725978409,"updated":1725978438},{"id":"66e0556b4ade4d0000393a82","text":"","created":1725977963,"updated":1725977963},{"id":"66e0557b4ade4d0000393a84","text":"","created":1725977980,"updated":1725977980},{"id":"66dfc00a4ade4d0000393a77","text":"[My first Eurorack] 3rd Edition","created":1725939723,"updated":1725939732},{"id":"66dfc0154ade4d0000393a79","text":"\t[https://www.youtube.com/watch?v=gbPE_iprwSA]","created":1725939733,"updated":1725939802},{"id":"66dfc05a4ade4d0000393a7a","text":"\t[Behringer] の [RS-9] これやんという気持ちになってきた","created":1725939802,"updated":1725939829},{"id":"66dfc30d4ade4d0000393a7e","text":"\t\t動画でも触れられているけど、値段がとってもリーズナブルそう","created":1725940494,"updated":1725940514},{"id":"66dfc3224ade4d0000393a7f","text":"\t\t[Erica Synths] の [Drum Sequencer] と比べると 1/10 くらいの値段で買えそう","created":1725940515,"updated":1725940552},{"id":"66dfc3484ade4d0000393a80","text":"\t\t\tまあ....[ラトビア]のクラフトマンたちに払ってもいいという気持ちもなくはないが....","created":1725940553,"updated":1725940576},{"id":"66dfc0754ade4d0000393a7c","text":"\t[https://www.youtube.com/watch?v=Py0P1zEh0_o]","created":1725939829,"updated":1725940098},{"id":"66dfc1814ade4d0000393a7d","text":"\t[Syncussion SY-1]","created":1725940098,"updated":1725940108},{"id":"66dfc00a4ade4d0000393a78","text":"","created":1725939723,"updated":1725939723}]}