{"id":"69fa079775c6350ffa571a6f","title":"The Invincible 感想 (ネタバレあり)","image":null,"created":1777993624,"updated":1777993628,"lines":[{"id":"69fa079775c6350ffa571a6f","text":"The Invincible 感想 (ネタバレあり)","created":1777993624,"updated":1777993624},{"id":"69fa0797000000000070c324","text":"from [20260503] #0503","created":1777993624,"updated":1777993628},{"id":"69fa0797000000000070c325","text":"[The Invincible] 感想 (ネタバレあり)","created":1777993624,"updated":1777993624},{"id":"69fa0797000000000070c326","text":"\t[レトロフューチャー]なテイストの[ウォーキングシム]っぽい [SF] [ADV]","created":1777993624,"updated":1777993624},{"id":"69fa0797000000000070c327","text":"\t\tレトロフューチャーといえば、直近[闇の精神史]で、レトロフューチャーには未来があるけど、現実にはそれがない、そういう意味ではレトロフューチャーや[アフロフューチャー]は[ユートピア]なのだという言を聞いていたので、まさしくレトロフューチャー満開の宇宙開拓を果たした人類を経験できるのはかなり良かった","created":1777993624,"updated":1777993624},{"id":"69fa0797000000000070c328","text":"\t\t道中、謎解きっぽいギミックはほぼなく、艦長と無線通信の周波数を切り替えるのにちょびっとギミックがあったぐらいで、あとは終始「どこそこへ向かえ～」というのをこなしていくだけ","created":1777993624,"updated":1777993624},{"id":"69fa0797000000000070c329","text":"\t\tなので、これで手触りがショボかったらしんどいが、[Fallout] ともまた違うレトロフューチャー感がよく作り込まれていて、最後まで飽きなかった","created":1777993624,"updated":1777993624},{"id":"69fa0797000000000070c32a","text":"\t\t\t唯一の気になりは、連合と連邦が英語が共通語でコミュニケートできているあたりかなあ","created":1777993624,"updated":1777993624},{"id":"69fa0797000000000070c32b","text":"\t\t\t連合のロヒトラとフツーに言葉が通じてコミュニケートできるのだけど.....そこはやっぱり言葉が通じないながらも通ずるモノがあって～～～みたいな展開の方がよくなかった？","created":1777993624,"updated":1777993624},{"id":"69fa0797000000000070c32c","text":"\t原作は[ポーランド]/[ウクライナ]の作家[スタニスワフ・レム]のものらしい","created":1777993624,"updated":1777993624},{"id":"69fa0797000000000070c32d","text":"\t\t結末としては、タイトルの Invincible は、劇中登場する連合のインビンシブル号のことではなく、レギスIIIにて自己増殖的に進化していった機械の最終形態である The Fly を指しているっぽい","created":1777993624,"updated":1777993624},{"id":"69fa0797000000000070c32e","text":"\t\tレギスIII のあらましとしては","created":1777993624,"updated":1777993624},{"id":"69fa0797000000000070c32f","text":"\t\t\t(おそらく)レル星の知的生命体が入植のためこのレギスIIIにやってきたのだが、うっかり母船の中の生命体が滅んじまって、機械だけが星に着陸してしまった","created":1777993624,"updated":1777993624},{"id":"69fa0797000000000070c330","text":"\t\t\t機械たちは、いもしない主のために都市を建設し、住居などを建設していった","created":1777993624,"updated":1777993624},{"id":"69fa0797000000000070c331","text":"\t\t\tその過程で、原生生物たちとの争いになり、それぞれ特化した機械を機械が設計して生産し、対抗していった","created":1777993624,"updated":1777993624},{"id":"69fa0797000000000070c332","text":"\t\t\t甲斐あって原生生物との戦いには勝ったが、今度は機械同士でリソースの分配を巡って争いになり、ある種は植物のように進化を果たし、またある種は昆虫のように進化を果たして機械同士の最終戦争がはじまった","created":1777993624,"updated":1777993624},{"id":"69fa0797000000000070c333","text":"\t\t\tそして、それに勝ったのが The Fly と名付けられたマイクロボットで、コイツらは","created":1777993624,"updated":1777993624},{"id":"69fa0797000000000070c334","text":"\t大まかには綺麗な三幕構成で、1幕では記憶喪失の主人公・ヤスナが<都市>を発見するも、クルーのほとんどを喪い、脱出船が高速に大気圏突入をカマしてきたせいで粉砕されてしまい、レギスIIIで[火星の人]状態になってしまう","created":1777993624,"updated":1777993624},{"id":"69fa0797000000000070c335","text":"\t2幕では連合が実はもう既に到着していて、いろいろ採掘や研究していたことが判明し、彼ら/彼女らの足跡を辿った結果、隠れ家にて暮らしている連中がいることが判明し、そこへ向かう","created":1777993624,"updated":1777993624},{"id":"69fa0797000000000070c336","text":"\t3幕では連合のロヒトラと The Fly に敵討ちするのに同調しつつ、コンドル号にてロヒトラが水爆をぶっ放して The Fly を根絶やしにするか、インビンシブル号を待って脱出するかの選択を～というような流れ","created":1777993624,"updated":1777993624},{"id":"69fa0797000000000070c337","text":"\t全体的には小品のゲームという感じではあるが、妙に高圧的な艦長、やや反抗的な主人公と微妙にノレるんだかノレないんだか微妙なところで、途中ちょっとウンザリもしかけたがまあ、ラストまで辿り着けはした","created":1777993624,"updated":1777993624},{"id":"69fa0797000000000070c338","text":"\t\t一応マルチエンドっぽいが、まー全部空けるほどかというと.....という感はやや","created":1777993624,"updated":1777993624},{"id":"69fa0797000000000070c339","text":"\t\t手触りは一級品だったから、このテイストで [The Outer Worlds] みたいにオープンワールドの惑星開拓のゲームだったりしたらもっと楽しめそうかな～","created":1777993624,"updated":1777993624},{"id":"69fa0797000000000070c33a","text":"","created":1777993624,"updated":1777993624}]}